LICENSE
MANIFEST.in
README.rst
setup.py
contacto/__init__.py
contacto/__main__.py
contacto/cli.py
contacto/gui.py
contacto/helpers.py
contacto/serial.py
contacto/storage.py
contacto/view.py
contacto.egg-info/PKG-INFO
contacto.egg-info/SOURCES.txt
contacto.egg-info/dependency_links.txt
contacto.egg-info/entry_points.txt
contacto.egg-info/not-zip-safe
contacto.egg-info/requires.txt
contacto.egg-info/top_level.txt
contacto/resources/about.html
contacto/resources/dml.sql
contacto/resources/mainwindow.ui
tests/helpers.py
tests/test_cli.py
tests/test_helpers.py
tests/test_serial.py
tests/test_storage.py
tests/test_view.py
tests/fixtures/cat.jpg
tests/fixtures/test.yml
tests/fixtures/tinybin.dat