Metadata-Version: 2.1
Name: contacto
Version: 0.2.1
Summary: A robust contact manager for social engineering.
Home-page: https://github.com/Dawnflash/contacto
Author: Adam Zahumensky
Author-email: zahumada@fit.cvut.cz
License: GNU General Public License v3 (GPLv3)
Keywords: contacts,social engineering,Qt,cli
Platform: UNKNOWN
Classifier: Intended Audience :: Developers
Classifier: License :: OSI Approved :: GNU General Public License v3 (GPLv3)
Classifier: Operating System :: OS Independent
Classifier: Programming Language :: Python :: 3.6
Classifier: Environment :: Console
Classifier: Environment :: X11 Applications :: Qt
Requires-Python: >=3.6
Provides-Extra: dev
